LICENSE
MANIFEST.in
README.md
pyproject.toml
src/mindroot/__init__.py
src/mindroot/migrate.py
src/mindroot/protocols.py
src/mindroot/server.py
src/mindroot/server_missing_normal_args.py
src/mindroot/server_prev.py
src/mindroot/services.py
src/mindroot.egg-info/PKG-INFO
src/mindroot.egg-info/SOURCES.txt
src/mindroot.egg-info/dependency_links.txt
src/mindroot.egg-info/entry_points.txt
src/mindroot.egg-info/requires.txt
src/mindroot.egg-info/top_level.txt
src/mindroot/coreplugins/__init__.py
src/mindroot/coreplugins/admin/__init__.py
src/mindroot/coreplugins/admin/agent_importer.py
src/mindroot/coreplugins/admin/agent_router.py
src/mindroot/coreplugins/admin/asset_manager.py
src/mindroot/coreplugins/admin/command_router.py
src/mindroot/coreplugins/admin/mcp_catalog_routes.py
src/mindroot/coreplugins/admin/mcp_publish_routes.py
src/mindroot/coreplugins/admin/mcp_registry_routes.py
src/mindroot/coreplugins/admin/mcp_routes.py
src/mindroot/coreplugins/admin/mod.py
src/mindroot/coreplugins/admin/oauth_callback_router.py
src/mindroot/coreplugins/admin/persona_handler.py
src/mindroot/coreplugins/admin/persona_router.py
src/mindroot/coreplugins/admin/plugin_manager.py
src/mindroot/coreplugins/admin/plugin_router.py
src/mindroot/coreplugins/admin/plugin_router_fixed.py
src/mindroot/coreplugins/admin/plugin_router_new_not_working.py
src/mindroot/coreplugins/admin/plugin_routes.py
src/mindroot/coreplugins/admin/registry_settings_routes.py
src/mindroot/coreplugins/admin/router.py
src/mindroot/coreplugins/admin/server_router.py
src/mindroot/coreplugins/admin/service_models.py
src/mindroot/coreplugins/admin/settings_router.py
src/mindroot/coreplugins/admin/static/logo.png
src/mindroot/coreplugins/admin/static/css/admin-custom.css
src/mindroot/coreplugins/admin/static/css/dark.css
src/mindroot/coreplugins/admin/static/css/default.css
src/mindroot/coreplugins/admin/static/css/detailstabs.css
src/mindroot/coreplugins/admin/static/css/reset.css
src/mindroot/coreplugins/admin/static/css/update.css
src/mindroot/coreplugins/admin/static/js/about-info.js
src/mindroot/coreplugins/admin/static/js/agent-editor.js
src/mindroot/coreplugins/admin/static/js/agent-form.js
