Metadata-Version: 2.4
Name: mindroot
Version: 11.17.0
Summary: MindRoot AI Agent Framework
Requires-Python: >=3.9
License-File: LICENSE
Requires-Dist: fastapi
Requires-Dist: uvicorn
Requires-Dist: jinja2
Requires-Dist: python-multipart
Requires-Dist: aiofiles
Requires-Dist: nanoid
Requires-Dist: termcolor
Requires-Dist: colored
Requires-Dist: loguru
Requires-Dist: pytz
Requires-Dist: PyJWT
Requires-Dist: pluggy
Requires-Dist: sse_starlette
Requires-Dist: partial-json-parser
Requires-Dist: setuptools
Requires-Dist: requests
Requires-Dist: aiohttp
Requires-Dist: Pillow
Requires-Dist: psutil
Requires-Dist: aiosmtplib
Requires-Dist: pydantic[email]
Requires-Dist: bcrypt
Requires-Dist: rich
Requires-Dist: colorama
Requires-Dist: python-dotenv
Requires-Dist: google-auth
Requires-Dist: google-auth-oauthlib
Requires-Dist: google-auth-httplib2
Requires-Dist: chardet
Requires-Dist: mcp>=1.12.3
Requires-Dist: httpx>=0.24.0
Requires-Dist: pydantic>=2.0.0
Requires-Dist: aiofiles>=23.0.0
Requires-Dist: uv>=0.7.0
Requires-Dist: textual>=0.88.0
Requires-Dist: pyperclip>=1.8.0
Requires-Dist: pyinstrument
Dynamic: license-file
